[
  {"palavra":"hospital","dica":"Local onde pessoas recebem atendimento médico"},
  {"palavra":"médico","dica":"Profissional que diagnostica e trata doenças"},
  {"palavra":"enfermeiro","dica":"Profissional que auxilia no cuidado de pacientes"},
  {"palavra":"farmácia","dica":"Local onde são vendidos medicamentos"},
  {"palavra":"remédio","dica":"Produto usado para tratar ou aliviar sintomas"},
  {"palavra":"vacina","dica":"Substância que ajuda a prevenir doenças"},
  {"palavra":"exame","dica":"Avaliação usada para verificar a saúde"},
  {"palavra":"consulta","dica":"Atendimento feito por um profissional de saúde"},
  {"palavra":"paciente","dica":"Pessoa que recebe atendimento de saúde"},
  {"palavra":"saúde","dica":"Estado de bem-estar físico e mental"},
  {"palavra":"doença","dica":"Condição que prejudica o funcionamento do corpo"},
  {"palavra":"febre","dica":"Aumento anormal da temperatura do corpo"},
  {"palavra":"tosse","dica":"Reflexo que expulsa ar dos pulmões pela boca"},
  {"palavra":"dor","dica":"Sensação desagradável em alguma parte do corpo"},
  {"palavra":"curativo","dica":"Proteção colocada sobre um ferimento"},
  {"palavra":"soro","dica":"Líquido usado para hidratar ou tratar pacientes"},
  {"palavra":"máscara","dica":"Objeto usado para cobrir boca e nariz"},
  {"palavra":"sabonete","dica":"Produto usado para lavar a pele"},
  {"palavra":"toalha","dica":"Tecido usado para secar o corpo ou objetos"},
  {"palavra":"escova","dica":"Objeto usado para limpar ou pentear"},
  {"palavra":"pente","dica":"Objeto usado para desembaraçar cabelos"},
  {"palavra":"perfume","dica":"Produto usado para deixar cheiro agradável"},
  {"palavra":"shampoo","dica":"Produto usado para lavar os cabelos"},
  {"palavra":"roupa","dica":"Peça usada para vestir o corpo"},
  {"palavra":"camisa","dica":"Peça de roupa usada na parte de cima do corpo"},
  {"palavra":"calça","dica":"Peça de roupa usada nas pernas"},
  {"palavra":"vestido","dica":"Peça de roupa inteira, geralmente sem divisão entre blusa e saia"},
  {"palavra":"sapato","dica":"Calçado fechado usado nos pés"},
  {"palavra":"meia","dica":"Peça usada para cobrir os pés"},
  {"palavra":"chinelo","dica":"Calçado leve e aberto"},
  {"palavra":"boné","dica":"Acessório com aba usado na cabeça"},
  {"palavra":"casaco","dica":"Roupa usada para proteger do frio"},
  {"palavra":"bolsa","dica":"Objeto usado para carregar pertences"},
  {"palavra":"carteira","dica":"Objeto usado para guardar dinheiro e documentos"},
  {"palavra":"chave","dica":"Objeto usado para abrir fechaduras"},
  {"palavra":"relógio","dica":"Objeto usado para marcar ou mostrar as horas"},
  {"palavra":"óculos","dica":"Objeto usado para corrigir ou proteger a visão"},
  {"palavra":"anel","dica":"Acessório usado no dedo"},
  {"palavra":"brinco","dica":"Acessório usado na orelha"},
  {"palavra":"colar","dica":"Acessório usado ao redor do pescoço"},
  {"palavra":"prato","dica":"Objeto usado para servir alimentos"},
  {"palavra":"copo","dica":"Objeto usado para beber líquidos"},
  {"palavra":"garfo","dica":"Talher usado para espetar alimentos"},
  {"palavra":"faca","dica":"Talher usado para cortar alimentos"},
  {"palavra":"colher","dica":"Talher usado para pegar líquidos ou alimentos macios"},
  {"palavra":"panela","dica":"Utensílio usado para cozinhar alimentos"},
  {"palavra":"forno","dica":"Equipamento usado para assar ou aquecer alimentos"},
  {"palavra":"microondas","dica":"Eletrodoméstico usado para aquecer alimentos rapidamente"},
  {"palavra":"liquidificador","dica":"Eletrodoméstico usado para triturar ou misturar alimentos"},
  {"palavra":"vassoura","dica":"Objeto usado para varrer o chão"},
  {"palavra":"rodo","dica":"Objeto usado para puxar água do chão"},
  {"palavra":"balde","dica":"Recipiente usado para carregar líquidos"},
  {"palavra":"sabão","dica":"Produto usado para lavar e limpar"},
  {"palavra":"detergente","dica":"Produto usado principalmente para lavar louça"},
  {"palavra":"esponja","dica":"Objeto usado para esfregar superfícies"},
  {"palavra":"lixo","dica":"Material descartado por não ter mais uso"},
  {"palavra":"jardim","dica":"Área com plantas, flores ou gramado"},
  {"palavra":"piscina","dica":"Reservatório de água usado para nadar"},
  {"palavra":"escada","dica":"Estrutura com degraus usada para subir ou descer"},
  {"palavra":"elevador","dica":"Equipamento que leva pessoas entre andares"},
  {"palavra":"mercado","dica":"Local onde se compram alimentos e produtos"},
  {"palavra":"padaria","dica":"Local onde são vendidos pães e outros alimentos"},
  {"palavra":"açougue","dica":"Local onde são vendidas carnes"},
  {"palavra":"banco","dica":"Instituição que guarda dinheiro e oferece serviços financeiros"},
  {"palavra":"correio","dica":"Serviço usado para enviar cartas e encomendas"},
  {"palavra":"igreja","dica":"Local destinado a culto religioso"},
  {"palavra":"hotel","dica":"Local que oferece hospedagem temporária"},
  {"palavra":"biblioteca","dica":"Local onde há livros para leitura ou empréstimo"},
  {"palavra":"museu","dica":"Local que guarda e expõe objetos históricos ou artísticos"},
  {"palavra":"restaurante","dica":"Local onde refeições são preparadas e servidas"},
  {"palavra":"loja","dica":"Estabelecimento onde produtos são vendidos"},
  {"palavra":"feira","dica":"Local com barracas para venda de produtos"},
  {"palavra":"ponte","dica":"Construção que permite passar sobre rio, vale ou estrada"},
  {"palavra":"túnel","dica":"Passagem construída por baixo da terra ou de uma montanha"},
  {"palavra":"estrada","dica":"Caminho preparado para circulação de veículos"},
  {"palavra":"rodovia","dica":"Estrada larga destinada ao tráfego de veículos"},
  {"palavra":"semáforo","dica":"Sinal luminoso que controla o trânsito"},
  {"palavra":"placa","dica":"Sinal usado para informar, orientar ou advertir"},
  {"palavra":"calçada","dica":"Parte da via destinada aos pedestres"},
  {"palavra":"esquina","dica":"Ponto onde duas ruas se encontram"},
  {"palavra":"bombeiro","dica":"Profissional que combate incêndios e faz resgates"},
  {"palavra":"policial","dica":"Profissional que atua na segurança pública"},
  {"palavra":"dentista","dica":"Profissional que cuida dos dentes"},
  {"palavra":"advogado","dica":"Profissional que trabalha com leis e defesa de direitos"},
  {"palavra":"padeiro","dica":"Profissional que prepara pães"},
  {"palavra":"cozinheiro","dica":"Profissional que prepara refeições"},
  {"palavra":"motorista","dica":"Pessoa que conduz veículos"},
  {"palavra":"piloto","dica":"Pessoa que conduz avião ou veículo de competição"},
  {"palavra":"vendedor","dica":"Pessoa que vende produtos ou serviços"},
  {"palavra":"agricultor","dica":"Pessoa que trabalha no cultivo da terra"},
  {"palavra":"martelo","dica":"Ferramenta usada para bater pregos"},
  {"palavra":"prego","dica":"Peça metálica usada para fixar materiais"},
  {"palavra":"serrote","dica":"Ferramenta usada para cortar madeira"},
  {"palavra":"alicate","dica":"Ferramenta usada para segurar, dobrar ou cortar"},
  {"palavra":"tesoura","dica":"Objeto usado para cortar papel, tecido ou outros materiais"},
  {"palavra":"cola","dica":"Produto usado para unir ou fixar materiais"},
  {"palavra":"papel","dica":"Material usado para escrever, imprimir ou desenhar"},
  {"palavra":"envelope","dica":"Objeto de papel usado para guardar cartas"},
  {"palavra":"jornal","dica":"Publicação com notícias e informações"},
  {"palavra":"revista","dica":"Publicação periódica com textos e imagens"}
]
